cxxbuild/__init__.py
cxxbuild/cxxbuild.py
cxxbuild-1.5.2.dist-info/LICENSE
cxxbuild-1.5.2.dist-info/METADATA
cxxbuild-1.5.2.dist-info/WHEEL
cxxbuild-1.5.2.dist-info/entry_points.txt
cxxbuild-1.5.2.dist-info/top_level.txt
cxxbuild-1.5.2.dist-info/RECORD
