Metadata-Version: 2.1
Name: cxxbuild
Version: 1.5.2
Summary: CxxBuild is a python script to easily build C++ programs: just invoke 'cxxbuild' and it works!
Author-email: Igor Machado Coelho <igormcoelho@proton.me>
License: MIT License
Project-URL: Homepage, https://github.com/manydeps/cxxbuild
Keywords: build,cplusplus,dependencies,cxxdeps,cmake,bazel
Classifier: License :: OSI Approved :: MIT License
Classifier: Programming Language :: Python
Classifier: Programming Language :: Python :: 3
Requires-Python: >=3.9
License-File: LICENSE
Requires-Dist: toml
Provides-Extra: dev
Requires-Dist: black ; extra == 'dev'
Requires-Dist: bumpver ; extra == 'dev'
Requires-Dist: isort ; extra == 'dev'
Requires-Dist: pip-tools ; extra == 'dev'
Requires-Dist: pytest ; extra == 'dev'
